[
    {
        "coordinates": [
            [
                439,
                282
            ],
            [
                439,
                262
            ],
            [
                477,
                262
            ],
            [
                477,
                282
            ]
        ]
    },
    {
        "coordinates": [
            [
                605,
                474
            ],
            [
                604,
                473
            ],
            [
                603,
                473
            ],
            [
                602,
                472
            ],
            [
                601,
                472
            ],
            [
                600,
                471
            ],
            [
                599,
                471
            ],
            [
                598,
                470
            ],
            [
                597,
                470
            ],
            [
                595,
                468
            ],
            [
                594,
                468
            ],
            [
                593,
                467
            ],
            [
                592,
                467
            ],
            [
                592,
                465
            ],
            [
                593,
                464
            ],
            [
                593,
                463
            ],
            [
                594,
                462
            ],
            [
                594,
                461
            ],
            [
                596,
                459
            ],
            [
                596,
                458
            ],
            [
                597,
                457
            ],
            [
                597,
                456
            ],
            [
                598,
                455
            ],
            [
                598,
                454
            ],
            [
                599,
                453
            ],
            [
                599,
                452
            ],
            [
                600,
                451
            ],
            [
                600,
                450
            ],
            [
                602,
                450
            ],
            [
                603,
                451
            ],
            [
                604,
                451
            ],
            [
                605,
                452
            ],
            [
                606,
                452
            ],
            [
                608,
                454
            ],
            [
                609,
                454
            ],
            [
                610,
                455
            ],
            [
                611,
                455
            ],
            [
                612,
                456
            ],
            [
                613,
                456
            ],
            [
                614,
                457
            ],
            [
                614,
                458
            ],
            [
                613,
                459
            ],
            [
                613,
                460
            ],
            [
                611,
                462
            ],
            [
                611,
                463
            ],
            [
                610,
                464
            ],
            [
                610,
                465
            ],
            [
                609,
                466
            ],
            [
                609,
                467
            ],
            [
                608,
                468
            ],
            [
                608,
                469
            ],
            [
                607,
                470
            ],
            [
                607,
                471
            ],
            [
                606,
                472
            ],
            [
                606,
                473
            ]
        ]
    },
    {
        "coordinates": [
            [
                787,
                652
            ],
            [
                786,
                651
            ],
            [
                784,
                651
            ],
            [
                784,
                649
            ],
            [
                785,
                648
            ],
            [
                785,
                643
            ],
            [
                799,
                643
            ],
            [
                800,
                644
            ],
            [
                803,
                644
            ],
            [
                803,
                652
            ]
        ]
    },
    {
        "coordinates": [
            [
                825,
                653
            ],
            [
                824,
                652
            ],
            [
                813,
                652
            ],
            [
                813,
                648
            ],
            [
                814,
                647
            ],
            [
                814,
                644
            ],
            [
                835,
                644
            ],
            [
                835,
                653
            ]
        ]
    },
    {
        "coordinates": [
            [
                1006,
                689
            ],
            [
                1006,
                675
            ],
            [
                1019,
                675
            ],
            [
                1019,
                689
            ]
        ]
    },
    {
        "coordinates": [
            [
                46,
                712
            ],
            [
                45,
                711
            ],
            [
                0,
                711
            ],
            [
                0,
                664
            ],
            [
                21,
                664
            ],
            [
                22,
                665
            ],
            [
                45,
                665
            ],
            [
                46,
                666
            ],
            [
                63,
                666
            ],
            [
                63,
                712
            ]
        ]
    },
    {
        "coordinates": [
            [
                824,
                723
            ],
            [
                823,
                722
            ],
            [
                823,
                708
            ],
            [
                831,
                708
            ],
            [
                831,
                717
            ],
            [
                830,
                718
            ],
            [
                830,
                723
            ]
        ]
    },
    {
        "coordinates": [
            [
                278,
                724
            ],
            [
                277,
                723
            ],
            [
                254,
                723
            ],
            [
                253,
                722
            ],
            [
                231,
                722
            ],
            [
                230,
                721
            ],
            [
                207,
                721
            ],
            [
                206,
                720
            ],
            [
                183,
                720
            ],
            [
                182,
                719
            ],
            [
                159,
                719
            ],
            [
                158,
                718
            ],
            [
                135,
                718
            ],
            [
                134,
                717
            ],
            [
                111,
                717
            ],
            [
                110,
                716
            ],
            [
                97,
                716
            ],
            [
                97,
                695
            ],
            [
                98,
                694
            ],
            [
                98,
                671
            ],
            [
                99,
                670
            ],
            [
                99,
                661
            ],
            [
                112,
                661
            ],
            [
                113,
                662
            ],
            [
                136,
                662
            ],
            [
                137,
                663
            ],
            [
                160,
                663
            ],
            [
                161,
                664
            ],
            [
                184,
                664
            ],
            [
                185,
                665
            ],
            [
                208,
                665
            ],
            [
                209,
                666
            ],
            [
                232,
                666
            ],
            [
                233,
                667
            ],
            [
                256,
                667
            ],
            [
                257,
                668
            ],
            [
                280,
                668
            ],
            [
                281,
                669
            ],
            [
                293,
                669
            ],
            [
                293,
                670
            ],
            [
                292,
                671
            ],
            [
                292,
                694
            ],
            [
                291,
                695
            ],
            [
                291,
                718
            ],
            [
                290,
                719
            ],
            [
                290,
                724
            ]
        ]
    },
    {
        "coordinates": [
            [
                722,
                741
            ],
            [
                721,
                740
            ],
            [
                692,
                740
            ],
            [
                691,
                739
            ],
            [
                661,
                739
            ],
            [
                660,
                738
            ],
            [
                631,
                738
            ],
            [
                630,
                737
            ],
            [
                620,
                737
            ],
            [
                620,
                723
            ],
            [
                621,
                722
            ],
            [
                621,
                693
            ],
            [
                622,
                692
            ],
            [
                629,
                692
            ],
            [
                630,
                693
            ],
            [
                659,
                693
            ],
            [
                660,
                694
            ],
            [
                690,
                694
            ],
            [
                691,
                695
            ],
            [
                720,
                695
            ],
            [
                721,
                696
            ],
            [
                724,
                696
            ],
            [
                724,
                726
            ],
            [
                723,
                727
            ],
            [
                723,
                741
            ]
        ]
    },
    {
        "coordinates": [
            [
                1018,
                769
            ],
            [
                1017,
                768
            ],
            [
                1003,
                768
            ],
            [
                1003,
                742
            ],
            [
                1004,
                741
            ],
            [
                1004,
                717
            ],
            [
                1010,
                717
            ],
            [
                1011,
                718
            ],
            [
                1023,
                718
            ],
            [
                1023,
                769
            ]
        ]
    },
    {
        "coordinates": [
            [
                955,
                806
            ],
            [
                955,
                805
            ],
            [
                956,
                804
            ],
            [
                956,
                800
            ],
            [
                961,
                800
            ],
            [
                961,
                806
            ]
        ]
    },
    {
        "coordinates": [
            [
                0,
                809
            ],
            [
                0,
                770
            ],
            [
                2,
                770
            ],
            [
                2,
                775
            ],
            [
                1,
                776
            ],
            [
                1,
                809
            ]
        ]
    },
    {
        "coordinates": [
            [
                1001,
                815
            ],
            [
                1001,
                793
            ],
            [
                1023,
                793
            ],
            [
                1023,
                815
            ]
        ]
    },
    {
        "coordinates": [
            [
                1007,
                846
            ],
            [
                1007,
                832
            ],
            [
                1023,
                832
            ],
            [
                1023,
                846
            ]
        ]
    },
    {
        "coordinates": [
            [
                1015,
                863
            ],
            [
                1014,
                862
            ],
            [
                1006,
                862
            ],
            [
                1006,
                849
            ],
            [
                1007,
                848
            ],
            [
                1023,
                848
            ],
            [
                1023,
                863
            ]
        ]
    },
    {
        "coordinates": [
            [
                994,
                1024
            ],
            [
                994,
                1014
            ],
            [
                995,
                1013
            ],
            [
                995,
                997
            ],
            [
                1001,
                997
            ],
            [
                1002,
                996
            ],
            [
                1002,
                977
            ],
            [
                1003,
                976
            ],
            [
                1003,
                932
            ],
            [
                1004,
                931
            ],
            [
                1004,
                922
            ],
            [
                1003,
                921
            ],
            [
                997,
                921
            ],
            [
                997,
                907
            ],
            [
                998,
                906
            ],
            [
                998,
                878
            ],
            [
                1022,
                878
            ],
            [
                1023,
                879
            ],
            [
                1023,
                1024
            ]
        ]
    },
    {
        "coordinates": [
            [
                724,
                1024
            ],
            [
                724,
                997
            ],
            [
                723,
                996
            ],
            [
                720,
                996
            ],
            [
                720,
                964
            ],
            [
                723,
                964
            ],
            [
                724,
                963
            ],
            [
                724,
                931
            ],
            [
                725,
                930
            ],
            [
                725,
                878
            ],
            [
                726,
                877
            ],
            [
                726,
                857
            ],
            [
                730,
                857
            ],
            [
                731,
                858
            ],
            [
                737,
                858
            ],
            [
                738,
                857
            ],
            [
                738,
                842
            ],
            [
                737,
                841
            ],
            [
                730,
                841
            ],
            [
                729,
                840
            ],
            [
                684,
                840
            ],
            [
                683,
                841
            ],
            [
                683,
                845
            ],
            [
                682,
                845
            ],
            [
                681,
                844
            ],
            [
                634,
                844
            ],
            [
                634,
                830
            ],
            [
                635,
                829
            ],
            [
                635,
                778
            ],
            [
                654,
                778
            ],
            [
                655,
                779
            ],
            [
                685,
                779
            ],
            [
                685,
                781
            ],
            [
                686,
                782
            ],
            [
                702,
                782
            ],
            [
                703,
                783
            ],
            [
                754,
                783
            ],
            [
                755,
                784
            ],
            [
                756,
                784
            ],
            [
                758,
                782
            ],
            [
                758,
                781
            ],
            [
                767,
                781
            ],
            [
                768,
                782
            ],
            [
                805,
                782
            ],
            [
                805,
                822
            ],
            [
                804,
                823
            ],
            [
                804,
                848
            ],
            [
                780,
                848
            ],
            [
                779,
                849
            ],
            [
                779,
                856
            ],
            [
                780,
                857
            ],
            [
                785,
                857
            ],
            [
                785,
                900
            ],
            [
                784,
                901
            ],
            [
                784,
                952
            ],
            [
                783,
                953
            ],
            [
                783,
                1004
            ],
            [
                782,
                1005
            ],
            [
                782,
                1024
            ]
        ]
    },
    {
        "coordinates": [
            [
                630,
                1024
            ],
            [
                630,
                1021
            ],
            [
                631,
                1020
            ],
            [
                631,
                986
            ],
            [
                632,
                985
            ],
            [
                632,
                951
            ],
            [
                633,
                950
            ],
            [
                654,
                950
            ],
            [
                655,
                951
            ],
            [
                689,
                951
            ],
            [
                689,
                952
            ],
            [
                688,
                953
            ],
            [
                688,
                987
            ],
            [
                687,
                988
            ],
            [
                687,
                1022
            ],
            [
                686,
                1023
            ],
            [
                686,
                1024
            ]
        ]
    },
    {
        "coordinates": [
            [
                524,
                1024
            ],
            [
                524,
                991
            ],
            [
                525,
                990
            ],
            [
                525,
                978
            ],
            [
                524,
                977
            ],
            [
                510,
                977
            ],
            [
                510,
                938
            ],
            [
                511,
                937
            ],
            [
                511,
                914
            ],
            [
                517,
                914
            ],
            [
                518,
                915
            ],
            [
                526,
                915
            ],
            [
                527,
                914
            ],
            [
                527,
                896
            ],
            [
                526,
                895
            ],
            [
                515,
                895
            ],
            [
                515,
                858
            ],
            [
                584,
                858
            ],
            [
                585,
                859
            ],
            [
                586,
                859
            ],
            [
                586,
                895
            ],
            [
                571,
                895
            ],
            [
                570,
                896
            ],
            [
                570,
                898
            ],
            [
                569,
                899
            ],
            [
                569,
                994
            ],
            [
                568,
                995
            ],
            [
                568,
                1024
            ]
        ]
    },
    {
        "coordinates": [
            [
                4,
                1024
            ],
            [
                4,
                942
            ],
            [
                22,
                942
            ],
            [
                23,
                941
            ],
            [
                23,
                836
            ],
            [
                41,
                836
            ],
            [
                42,
                835
            ],
            [
                42,
                760
            ],
            [
                127,
                760
            ],
            [
                127,
                776
            ],
            [
                128,
                777
            ],
            [
                151,
                777
            ],
            [
                152,
                776
            ],
            [
                152,
                765
            ],
            [
                315,
                765
            ],
            [
                315,
                961
            ],
            [
                235,
                961
            ],
            [
                235,
                905
            ],
            [
                272,
                905
            ],
            [
                273,
                904
            ],
            [
                273,
                842
            ],
            [
                272,
                841
            ],
            [
                152,
                841
            ],
            [
                151,
                842
            ],
            [
                151,
                1024
            ]
        ]
    }
]