[
    {
        "coordinates": [
            [
                394,
                36
            ],
            [
                394,
                1
            ],
            [
                455,
                1
            ],
            [
                455,
                36
            ]
        ]
    },
    {
        "coordinates": [
            [
                255,
                37
            ],
            [
                255,
                1
            ],
            [
                294,
                1
            ],
            [
                294,
                37
            ]
        ]
    },
    {
        "coordinates": [
            [
                296,
                43
            ],
            [
                296,
                1
            ],
            [
                362,
                1
            ],
            [
                362,
                43
            ]
        ]
    },
    {
        "coordinates": [
            [
                659,
                61
            ],
            [
                659,
                1
            ],
            [
                713,
                1
            ],
            [
                713,
                61
            ]
        ]
    },
    {
        "coordinates": [
            [
                457,
                68
            ],
            [
                457,
                1
            ],
            [
                512,
                1
            ],
            [
                512,
                25
            ],
            [
                513,
                26
            ],
            [
                657,
                26
            ],
            [
                657,
                61
            ],
            [
                650,
                61
            ],
            [
                649,
                62
            ],
            [
                611,
                62
            ],
            [
                610,
                63
            ],
            [
                610,
                68
            ]
        ]
    },
    {
        "coordinates": [
            [
                348,
                80
            ],
            [
                348,
                69
            ],
            [
                347,
                68
            ],
            [
                347,
                61
            ],
            [
                386,
                61
            ],
            [
                387,
                60
            ],
            [
                425,
                60
            ],
            [
                425,
                78
            ],
            [
                409,
                78
            ],
            [
                408,
                79
            ],
            [
                367,
                79
            ],
            [
                366,
                80
            ]
        ]
    },
    {
        "coordinates": [
            [
                177,
                130
            ],
            [
                177,
                103
            ],
            [
                176,
                102
            ],
            [
                176,
                93
            ],
            [
                197,
                93
            ],
            [
                198,
                92
            ],
            [
                234,
                92
            ],
            [
                234,
                95
            ],
            [
                235,
                96
            ],
            [
                235,
                129
            ],
            [
                221,
                129
            ],
            [
                220,
                130
            ]
        ]
    },
    {
        "coordinates": [
            [
                423,
                132
            ],
            [
                423,
                103
            ],
            [
                422,
                102
            ],
            [
                421,
                103
            ],
            [
                421,
                123
            ],
            [
                414,
                123
            ],
            [
                413,
                124
            ],
            [
                382,
                124
            ],
            [
                381,
                125
            ],
            [
                351,
                125
            ],
            [
                350,
                126
            ],
            [
                320,
                126
            ],
            [
                319,
                127
            ],
            [
                289,
                127
            ],
            [
                288,
                128
            ],
            [
                258,
                128
            ],
            [
                257,
                129
            ],
            [
                237,
                129
            ],
            [
                237,
                102
            ],
            [
                251,
                102
            ],
            [
                252,
                101
            ],
            [
                283,
                101
            ],
            [
                284,
                100
            ],
            [
                315,
                100
            ],
            [
                316,
                99
            ],
            [
                346,
                99
            ],
            [
                347,
                98
            ],
            [
                378,
                98
            ],
            [
                379,
                97
            ],
            [
                410,
                97
            ],
            [
                411,
                96
            ],
            [
                420,
                96
            ],
            [
                420,
                102
            ],
            [
                421,
                103
            ],
            [
                422,
                102
            ],
            [
                422,
                96
            ],
            [
                452,
                96
            ],
            [
                453,
                95
            ],
            [
                498,
                95
            ],
            [
                499,
                94
            ],
            [
                526,
                94
            ],
            [
                526,
                130
            ],
            [
                487,
                130
            ],
            [
                486,
                131
            ],
            [
                439,
                131
            ],
            [
                438,
                132
            ]
        ]
    },
    {
        "coordinates": [
            [
                97,
                136
            ],
            [
                96,
                135
            ],
            [
                72,
                135
            ],
            [
                72,
                123
            ],
            [
                73,
                122
            ],
            [
                73,
                117
            ],
            [
                101,
                117
            ],
            [
                102,
                118
            ],
            [
                102,
                136
            ]
        ]
    },
    {
        "coordinates": [
            [
                588,
                140
            ],
            [
                587,
                139
            ],
            [
                587,
                138
            ],
            [
                586,
                137
            ],
            [
                586,
                135
            ],
            [
                585,
                134
            ],
            [
                585,
                133
            ],
            [
                584,
                132
            ],
            [
                584,
                131
            ],
            [
                583,
                130
            ],
            [
                569,
                130
            ],
            [
                569,
                108
            ],
            [
                568,
                107
            ],
            [
                568,
                90
            ],
            [
                572,
                90
            ],
            [
                573,
                89
            ],
            [
                660,
                89
            ],
            [
                661,
                88
            ],
            [
                744,
                88
            ],
            [
                744,
                105
            ],
            [
                745,
                106
            ],
            [
                745,
                124
            ],
            [
                732,
                124
            ],
            [
                731,
                125
            ],
            [
                695,
                125
            ],
            [
                694,
                126
            ],
            [
                658,
                126
            ],
            [
                657,
                127
            ],
            [
                639,
                127
            ],
            [
                637,
                129
            ],
            [
                637,
                135
            ],
            [
                636,
                136
            ],
            [
                636,
                139
            ],
            [
                621,
                139
            ],
            [
                620,
                140
            ]
        ]
    },
    {
        "coordinates": [
            [
                121,
                140
            ],
            [
                120,
                139
            ],
            [
                111,
                139
            ],
            [
                111,
                138
            ],
            [
                112,
                137
            ],
            [
                112,
                112
            ],
            [
                113,
                111
            ],
            [
                113,
                89
            ],
            [
                112,
                88
            ],
            [
                111,
                89
            ],
            [
                111,
                99
            ],
            [
                92,
                99
            ],
            [
                91,
                98
            ],
            [
                71,
                98
            ],
            [
                70,
                97
            ],
            [
                50,
                97
            ],
            [
                49,
                96
            ],
            [
                29,
                96
            ],
            [
                28,
                95
            ],
            [
                8,
                95
            ],
            [
                7,
                94
            ],
            [
                0,
                94
            ],
            [
                0,
                19
            ],
            [
                17,
                19
            ],
            [
                18,
                18
            ],
            [
                17,
                17
            ],
            [
                0,
                17
            ],
            [
                0,
                1
            ],
            [
                48,
                1
            ],
            [
                48,
                8
            ],
            [
                47,
                9
            ],
            [
                47,
                19
            ],
            [
                39,
                19
            ],
            [
                38,
                20
            ],
            [
                39,
                21
            ],
            [
                59,
                21
            ],
            [
                60,
                22
            ],
            [
                80,
                22
            ],
            [
                81,
                23
            ],
            [
                99,
                23
            ],
            [
                99,
                29
            ],
            [
                100,
                30
            ],
            [
                101,
                29
            ],
            [
                101,
                13
            ],
            [
                114,
                13
            ],
            [
                115,
                14
            ],
            [
                145,
                14
            ],
            [
                146,
                15
            ],
            [
                176,
                15
            ],
            [
                177,
                16
            ],
            [
                207,
                16
            ],
            [
                208,
                17
            ],
            [
                214,
                17
            ],
            [
                214,
                34
            ],
            [
                213,
                35
            ],
            [
                213,
                43
            ],
            [
                210,
                43
            ],
            [
                209,
                42
            ],
            [
                179,
                42
            ],
            [
                178,
                41
            ],
            [
                148,
                41
            ],
            [
                147,
                40
            ],
            [
                117,
                40
            ],
            [
                116,
                39
            ],
            [
                111,
                39
            ],
            [
                110,
                40
            ],
            [
                110,
                46
            ],
            [
                109,
                47
            ],
            [
                109,
                51
            ],
            [
                99,
                51
            ],
            [
                98,
                50
            ],
            [
                97,
                51
            ],
            [
                97,
                56
            ],
            [
                98,
                57
            ],
            [
                100,
                57
            ],
            [
                101,
                58
            ],
            [
                113,
                58
            ],
            [
                113,
                67
            ],
            [
                114,
                68
            ],
            [
                115,
                67
            ],
            [
                115,
                48
            ],
            [
                123,
                48
            ],
            [
                124,
                49
            ],
            [
                146,
                49
            ],
            [
                146,
                65
            ],
            [
                145,
                66
            ],
            [
                145,
                89
            ],
            [
                144,
                90
            ],
            [
                144,
                113
            ],
            [
                143,
                114
            ],
            [
                143,
                137
            ],
            [
                142,
                138
            ],
            [
                142,
                140
            ]
        ]
    },
    {
        "coordinates": [
            [
                589,
                158
            ],
            [
                589,
                156
            ],
            [
                588,
                155
            ],
            [
                588,
                142
            ],
            [
                607,
                142
            ],
            [
                607,
                157
            ],
            [
                603,
                157
            ],
            [
                602,
                158
            ]
        ]
    },
    {
        "coordinates": [
            [
                572,
                188
            ],
            [
                572,
                174
            ],
            [
                584,
                174
            ],
            [
                584,
                188
            ]
        ]
    },
    {
        "coordinates": [
            [
                69,
                198
            ],
            [
                69,
                166
            ],
            [
                124,
                166
            ],
            [
                124,
                198
            ]
        ]
    },
    {
        "coordinates": [
            [
                0,
                198
            ],
            [
                0,
                123
            ],
            [
                67,
                123
            ],
            [
                67,
                198
            ]
        ]
    },
    {
        "coordinates": [
            [
                843,
                250
            ],
            [
                843,
                62
            ],
            [
                842,
                61
            ],
            [
                842,
                1
            ],
            [
                880,
                1
            ],
            [
                880,
                3
            ],
            [
                881,
                4
            ],
            [
                881,
                232
            ],
            [
                882,
                233
            ],
            [
                882,
                250
            ]
        ]
    },
    {
        "coordinates": [
            [
                931,
                268
            ],
            [
                931,
                260
            ],
            [
                930,
                259
            ],
            [
                907,
                259
            ],
            [
                907,
                247
            ],
            [
                914,
                247
            ],
            [
                915,
                246
            ],
            [
                915,
                6
            ],
            [
                914,
                5
            ],
            [
                914,
                1
            ],
            [
                956,
                1
            ],
            [
                956,
                268
            ]
        ]
    },
    {
        "coordinates": [
            [
                983,
                304
            ],
            [
                983,
                212
            ],
            [
                982,
                211
            ],
            [
                982,
                117
            ],
            [
                981,
                116
            ],
            [
                981,
                23
            ],
            [
                980,
                22
            ],
            [
                980,
                1
            ],
            [
                999,
                1
            ],
            [
                999,
                62
            ],
            [
                1000,
                63
            ],
            [
                1001,
                62
            ],
            [
                1001,
                1
            ],
            [
                1023,
                1
            ],
            [
                1023,
                192
            ],
            [
                1003,
                192
            ],
            [
                1003,
                167
            ],
            [
                1002,
                166
            ],
            [
                1001,
                167
            ],
            [
                1001,
                245
            ],
            [
                1002,
                246
            ],
            [
                1002,
                303
            ],
            [
                998,
                303
            ],
            [
                997,
                304
            ]
        ]
    },
    {
        "coordinates": [
            [
                910,
                313
            ],
            [
                909,
                312
            ],
            [
                885,
                312
            ],
            [
                885,
                292
            ],
            [
                884,
                291
            ],
            [
                844,
                291
            ],
            [
                843,
                290
            ],
            [
                792,
                290
            ],
            [
                791,
                289
            ],
            [
                774,
                289
            ],
            [
                773,
                290
            ],
            [
                773,
                298
            ],
            [
                742,
                298
            ],
            [
                742,
                282
            ],
            [
                743,
                281
            ],
            [
                743,
                250
            ],
            [
                780,
                250
            ],
            [
                781,
                249
            ],
            [
                780,
                248
            ],
            [
                771,
                248
            ],
            [
                771,
                158
            ],
            [
                770,
                157
            ],
            [
                770,
                2
            ],
            [
                769,
                1
            ],
            [
                810,
                1
            ],
            [
                810,
                87
            ],
            [
                811,
                88
            ],
            [
                811,
                246
            ],
            [
                812,
                247
            ],
            [
                812,
                249
            ],
            [
                782,
                249
            ],
            [
                781,
                250
            ],
            [
                782,
                251
            ],
            [
                832,
                251
            ],
            [
                833,
                252
            ],
            [
                885,
                252
            ],
            [
                886,
                253
            ],
            [
                905,
                253
            ],
            [
                905,
                260
            ],
            [
                906,
                261
            ],
            [
                929,
                261
            ],
            [
                929,
                269
            ],
            [
                930,
                270
            ],
            [
                951,
                270
            ],
            [
                951,
                290
            ],
            [
                950,
                291
            ],
            [
                950,
                313
            ]
        ]
    },
    {
        "coordinates": [
            [
                678,
                333
            ],
            [
                677,
                332
            ],
            [
                644,
                332
            ],
            [
                644,
                322
            ],
            [
                645,
                321
            ],
            [
                645,
                303
            ],
            [
                665,
                303
            ],
            [
                666,
                302
            ],
            [
                666,
                258
            ],
            [
                667,
                257
            ],
            [
                667,
                211
            ],
            [
                705,
                211
            ],
            [
                706,
                210
            ],
            [
                705,
                209
            ],
            [
                666,
                209
            ],
            [
                665,
                210
            ],
            [
                665,
                224
            ],
            [
                651,
                224
            ],
            [
                650,
                223
            ],
            [
                649,
                223
            ],
            [
                649,
                191
            ],
            [
                650,
                190
            ],
            [
                650,
                187
            ],
            [
                679,
                187
            ],
            [
                680,
                188
            ],
            [
                707,
                188
            ],
            [
                707,
                195
            ],
            [
                706,
                196
            ],
            [
                706,
                210
            ],
            [
                705,
                211
            ],
            [
                706,
                212
            ],
            [
                706,
                238
            ],
            [
                705,
                239
            ],
            [
                705,
                279
            ],
            [
                704,
                280
            ],
            [
                704,
                302
            ],
            [
                666,
                302
            ],
            [
                665,
                303
            ],
            [
                666,
                304
            ],
            [
                704,
                304
            ],
            [
                704,
                325
            ],
            [
                703,
                326
            ],
            [
                703,
                333
            ]
        ]
    },
    {
        "coordinates": [
            [
                1003,
                348
            ],
            [
                1003,
                341
            ],
            [
                1002,
                340
            ],
            [
                1002,
                311
            ],
            [
                1014,
                311
            ],
            [
                1015,
                310
            ],
            [
                1018,
                310
            ],
            [
                1019,
                309
            ],
            [
                1019,
                297
            ],
            [
                1018,
                296
            ],
            [
                1018,
                273
            ],
            [
                1023,
                273
            ],
            [
                1023,
                347
            ],
            [
                1022,
                347
            ],
            [
                1021,
                348
            ]
        ]
    },
    {
        "coordinates": [
            [
                302,
                360
            ],
            [
                299,
                357
            ],
            [
                298,
                357
            ],
            [
                296,
                355
            ],
            [
                295,
                355
            ],
            [
                292,
                352
            ],
            [
                291,
                352
            ],
            [
                289,
                350
            ],
            [
                288,
                350
            ],
            [
                286,
                348
            ],
            [
                285,
                348
            ],
            [
                282,
                345
            ],
            [
                281,
                345
            ],
            [
                279,
                343
            ],
            [
                278,
                343
            ],
            [
                276,
                341
            ],
            [
                275,
                341
            ],
            [
                272,
                338
            ],
            [
                271,
                338
            ],
            [
                269,
                336
            ],
            [
                268,
                336
            ],
            [
                267,
                335
            ],
            [
                162,
                335
            ],
            [
                162,
                241
            ],
            [
                172,
                241
            ],
            [
                172,
                250
            ],
            [
                173,
                251
            ],
            [
                428,
                251
            ],
            [
                428,
                335
            ],
            [
                425,
                335
            ],
            [
                424,
                334
            ],
            [
                417,
                334
            ],
            [
                416,
                335
            ],
            [
                320,
                335
            ],
            [
                319,
                336
            ],
            [
                319,
                337
            ],
            [
                317,
                339
            ],
            [
                317,
                340
            ],
            [
                315,
                342
            ],
            [
                315,
                343
            ],
            [
                312,
                346
            ],
            [
                312,
                347
            ],
            [
                310,
                349
            ],
            [
                310,
                350
            ],
            [
                307,
                353
            ],
            [
                307,
                354
            ],
            [
                305,
                356
            ],
            [
                305,
                357
            ],
            [
                303,
                359
            ],
            [
                303,
                360
            ]
        ]
    },
    {
        "coordinates": [
            [
                6,
                397
            ],
            [
                5,
                396
            ],
            [
                3,
                396
            ],
            [
                2,
                395
            ],
            [
                1,
                395
            ],
            [
                0,
                394
            ],
            [
                0,
                260
            ],
            [
                11,
                260
            ],
            [
                12,
                259
            ],
            [
                12,
                256
            ],
            [
                92,
                256
            ],
            [
                92,
                258
            ],
            [
                91,
                259
            ],
            [
                92,
                260
            ],
            [
                113,
                260
            ],
            [
                113,
                288
            ],
            [
                114,
                289
            ],
            [
                114,
                368
            ],
            [
                115,
                369
            ],
            [
                115,
                383
            ],
            [
                113,
                385
            ],
            [
                113,
                386
            ],
            [
                112,
                387
            ],
            [
                112,
                388
            ],
            [
                107,
                393
            ],
            [
                106,
                393
            ],
            [
                105,
                394
            ],
            [
                104,
                394
            ],
            [
                103,
                395
            ],
            [
                101,
                395
            ],
            [
                100,
                396
            ],
            [
                98,
                396
            ],
            [
                97,
                397
            ],
            [
                87,
                397
            ],
            [
                86,
                396
            ],
            [
                84,
                396
            ],
            [
                83,
                395
            ],
            [
                81,
                395
            ],
            [
                80,
                394
            ],
            [
                79,
                394
            ],
            [
                78,
                393
            ],
            [
                77,
                393
            ],
            [
                75,
                391
            ],
            [
                74,
                391
            ],
            [
                74,
                390
            ],
            [
                71,
                387
            ],
            [
                71,
                386
            ],
            [
                70,
                385
            ],
            [
                69,
                385
            ],
            [
                68,
                386
            ],
            [
                68,
                393
            ],
            [
                64,
                393
            ],
            [
                63,
                392
            ],
            [
                37,
                392
            ],
            [
                37,
                386
            ],
            [
                36,
                385
            ],
            [
                35,
                385
            ],
            [
                33,
                387
            ],
            [
                33,
                388
            ],
            [
                30,
                391
            ],
            [
                29,
                391
            ],
            [
                27,
                393
            ],
            [
                26,
                393
            ],
            [
                25,
                394
            ],
            [
                24,
                394
            ],
            [
                23,
                395
            ],
            [
                21,
                395
            ],
            [
                20,
                396
            ],
            [
                15,
                396
            ],
            [
                14,
                397
            ]
        ]
    },
    {
        "coordinates": [
            [
                161,
                410
            ],
            [
                161,
                398
            ],
            [
                162,
                397
            ],
            [
                162,
                370
            ],
            [
                265,
                370
            ],
            [
                265,
                410
            ]
        ]
    },
    {
        "coordinates": [
            [
                603,
                413
            ],
            [
                603,
                376
            ],
            [
                701,
                376
            ],
            [
                701,
                413
            ]
        ]
    },
    {
        "coordinates": [
            [
                705,
                421
            ],
            [
                705,
                409
            ],
            [
                719,
                409
            ],
            [
                719,
                421
            ]
        ]
    },
    {
        "coordinates": [
            [
                773,
                426
            ],
            [
                773,
                391
            ],
            [
                842,
                391
            ],
            [
                843,
                390
            ],
            [
                980,
                390
            ],
            [
                980,
                425
            ],
            [
                880,
                425
            ],
            [
                879,
                426
            ]
        ]
    },
    {
        "coordinates": [
            [
                450,
                426
            ],
            [
                450,
                418
            ],
            [
                449,
                417
            ],
            [
                430,
                417
            ],
            [
                430,
                251
            ],
            [
                435,
                251
            ],
            [
                436,
                250
            ],
            [
                493,
                250
            ],
            [
                494,
                249
            ],
            [
                520,
                249
            ],
            [
                521,
                250
            ],
            [
                542,
                250
            ],
            [
                542,
                280
            ],
            [
                543,
                281
            ],
            [
                543,
                310
            ],
            [
                484,
                310
            ],
            [
                483,
                311
            ],
            [
                481,
                311
            ],
            [
                480,
                312
            ],
            [
                480,
                369
            ],
            [
                481,
                370
            ],
            [
                482,
                369
            ],
            [
                482,
                352
            ],
            [
                497,
                352
            ],
            [
                498,
                351
            ],
            [
                542,
                351
            ],
            [
                542,
                361
            ],
            [
                543,
                362
            ],
            [
                543,
                406
            ],
            [
                483,
                406
            ],
            [
                483,
                371
            ],
            [
                482,
                370
            ],
            [
                481,
                371
            ],
            [
                481,
                425
            ],
            [
                452,
                425
            ],
            [
                451,
                426
            ]
        ]
    },
    {
        "coordinates": [
            [
                1013,
                435
            ],
            [
                1013,
                405
            ],
            [
                1023,
                405
            ],
            [
                1023,
                435
            ]
        ]
    },
    {
        "coordinates": [
            [
                76,
                435
            ],
            [
                76,
                412
            ],
            [
                100,
                412
            ],
            [
                100,
                435
            ]
        ]
    },
    {
        "coordinates": [
            [
                510,
                628
            ],
            [
                509,
                627
            ],
            [
                359,
                627
            ],
            [
                359,
                586
            ],
            [
                397,
                586
            ],
            [
                398,
                587
            ],
            [
                566,
                587
            ],
            [
                566,
                628
            ]
        ]
    },
    {
        "coordinates": [
            [
                1,
                629
            ],
            [
                1,
                589
            ],
            [
                71,
                589
            ],
            [
                72,
                588
            ],
            [
                205,
                588
            ],
            [
                205,
                628
            ],
            [
                163,
                628
            ],
            [
                162,
                629
            ]
        ]
    },
    {
        "coordinates": [
            [
                819,
                633
            ],
            [
                819,
                595
            ],
            [
                875,
                595
            ],
            [
                875,
                598
            ],
            [
                876,
                599
            ],
            [
                893,
                599
            ],
            [
                894,
                598
            ],
            [
                894,
                593
            ],
            [
                952,
                593
            ],
            [
                952,
                597
            ],
            [
                953,
                598
            ],
            [
                971,
                598
            ],
            [
                972,
                597
            ],
            [
                972,
                594
            ],
            [
                1023,
                594
            ],
            [
                1023,
                632
            ],
            [
                821,
                632
            ],
            [
                820,
                633
            ]
        ]
    },
    {
        "coordinates": [
            [
                349,
                695
            ],
            [
                349,
                680
            ],
            [
                350,
                679
            ],
            [
                365,
                679
            ],
            [
                365,
                695
            ]
        ]
    },
    {
        "coordinates": [
            [
                924,
                756
            ],
            [
                924,
                671
            ],
            [
                986,
                671
            ],
            [
                986,
                756
            ]
        ]
    },
    {
        "coordinates": [
            [
                780,
                780
            ],
            [
                780,
                766
            ],
            [
                779,
                765
            ],
            [
                779,
                671
            ],
            [
                778,
                670
            ],
            [
                778,
                634
            ],
            [
                815,
                634
            ],
            [
                816,
                633
            ],
            [
                815,
                632
            ],
            [
                778,
                632
            ],
            [
                778,
                615
            ],
            [
                777,
                614
            ],
            [
                698,
                614
            ],
            [
                698,
                593
            ],
            [
                717,
                593
            ],
            [
                718,
                592
            ],
            [
                718,
                578
            ],
            [
                728,
                578
            ],
            [
                729,
                579
            ],
            [
                734,
                579
            ],
            [
                736,
                577
            ],
            [
                736,
                557
            ],
            [
                747,
                557
            ],
            [
                748,
                558
            ],
            [
                756,
                558
            ],
            [
                757,
                557
            ],
            [
                757,
                549
            ],
            [
                778,
                549
            ],
            [
                778,
                550
            ],
            [
                777,
                551
            ],
            [
                777,
                557
            ],
            [
                779,
                559
            ],
            [
                817,
                559
            ],
            [
                817,
                668
            ],
            [
                818,
                669
            ],
            [
                818,
                765
            ],
            [
                819,
                766
            ],
            [
                819,
                780
            ]
        ]
    },
    {
        "coordinates": [
            [
                857,
                808
            ],
            [
                856,
                807
            ],
            [
                853,
                807
            ],
            [
                853,
                786
            ],
            [
                891,
                786
            ],
            [
                891,
                808
            ]
        ]
    },
    {
        "coordinates": [
            [
                193,
                808
            ],
            [
                193,
                788
            ],
            [
                203,
                788
            ],
            [
                204,
                787
            ],
            [
                228,
                787
            ],
            [
                229,
                786
            ],
            [
                229,
                803
            ],
            [
                230,
                804
            ],
            [
                230,
                807
            ],
            [
                203,
                807
            ],
            [
                202,
                808
            ]
        ]
    },
    {
        "coordinates": [
            [
                584,
                810
            ],
            [
                584,
                692
            ],
            [
                583,
                691
            ],
            [
                583,
                629
            ],
            [
                582,
                628
            ],
            [
                568,
                628
            ],
            [
                568,
                604
            ],
            [
                619,
                604
            ],
            [
                620,
                603
            ],
            [
                629,
                603
            ],
            [
                629,
                734
            ],
            [
                630,
                735
            ],
            [
                630,
                810
            ]
        ]
    },
    {
        "coordinates": [
            [
                260,
                812
            ],
            [
                260,
                718
            ],
            [
                259,
                717
            ],
            [
                259,
                610
            ],
            [
                274,
                610
            ],
            [
                275,
                609
            ],
            [
                274,
                608
            ],
            [
                207,
                608
            ],
            [
                207,
                564
            ],
            [
                332,
                564
            ],
            [
                333,
                565
            ],
            [
                357,
                565
            ],
            [
                357,
                609
            ],
            [
                277,
                609
            ],
            [
                276,
                610
            ],
            [
                277,
                611
            ],
            [
                301,
                611
            ],
            [
                301,
                688
            ],
            [
                302,
                689
            ],
            [
                302,
                811
            ],
            [
                295,
                811
            ],
            [
                294,
                812
            ]
        ]
    },
    {
        "coordinates": [
            [
                375,
                813
            ],
            [
                374,
                812
            ],
            [
                350,
                812
            ],
            [
                350,
                791
            ],
            [
                359,
                791
            ],
            [
                360,
                790
            ],
            [
                360,
                769
            ],
            [
                385,
                769
            ],
            [
                386,
                770
            ],
            [
                392,
                770
            ],
            [
                393,
                769
            ],
            [
                393,
                752
            ],
            [
                411,
                752
            ],
            [
                412,
                753
            ],
            [
                414,
                753
            ],
            [
                414,
                775
            ],
            [
                413,
                776
            ],
            [
                413,
                813
            ]
        ]
    },
    {
        "coordinates": [
            [
                796,
                815
            ],
            [
                796,
                804
            ],
            [
                795,
                803
            ],
            [
                795,
                796
            ],
            [
                817,
                796
            ],
            [
                818,
                795
            ],
            [
                837,
                795
            ],
            [
                837,
                798
            ],
            [
                838,
                799
            ],
            [
                838,
                815
            ]
        ]
    },
    {
        "coordinates": [
            [
                92,
                879
            ],
            [
                92,
                674
            ],
            [
                136,
                674
            ],
            [
                136,
                757
            ],
            [
                137,
                758
            ],
            [
                137,
                879
            ]
        ]
    },
    {
        "coordinates": [
            [
                326,
                899
            ],
            [
                325,
                898
            ],
            [
                325,
                896
            ],
            [
                326,
                895
            ],
            [
                326,
                866
            ],
            [
                335,
                866
            ],
            [
                336,
                867
            ],
            [
                356,
                867
            ],
            [
                356,
                872
            ],
            [
                355,
                873
            ],
            [
                355,
                899
            ]
        ]
    },
    {
        "coordinates": [
            [
                672,
                902
            ],
            [
                672,
                876
            ],
            [
                671,
                875
            ],
            [
                671,
                862
            ],
            [
                673,
                862
            ],
            [
                674,
                861
            ],
            [
                686,
                861
            ],
            [
                687,
                860
            ],
            [
                687,
                854
            ],
            [
                733,
                854
            ],
            [
                733,
                860
            ],
            [
                734,
                861
            ],
            [
                759,
                861
            ],
            [
                760,
                860
            ],
            [
                760,
                854
            ],
            [
                768,
                854
            ],
            [
                769,
                853
            ],
            [
                800,
                853
            ],
            [
                800,
                859
            ],
            [
                801,
                860
            ],
            [
                831,
                860
            ],
            [
                832,
                859
            ],
            [
                832,
                853
            ],
            [
                875,
                853
            ],
            [
                875,
                858
            ],
            [
                876,
                859
            ],
            [
                892,
                859
            ],
            [
                892,
                900
            ],
            [
                868,
                900
            ],
            [
                868,
                896
            ],
            [
                867,
                895
            ],
            [
                840,
                895
            ],
            [
                839,
                896
            ],
            [
                839,
                901
            ],
            [
                795,
                901
            ],
            [
                795,
                896
            ],
            [
                794,
                895
            ],
            [
                768,
                895
            ],
            [
                767,
                896
            ],
            [
                767,
                901
            ],
            [
                758,
                901
            ],
            [
                757,
                902
            ],
            [
                724,
                902
            ],
            [
                724,
                897
            ],
            [
                723,
                896
            ],
            [
                695,
                896
            ],
            [
                694,
                897
            ],
            [
                694,
                902
            ]
        ]
    },
    {
        "coordinates": [
            [
                464,
                906
            ],
            [
                464,
                874
            ],
            [
                485,
                874
            ],
            [
                486,
                875
            ],
            [
                487,
                875
            ],
            [
                487,
                886
            ],
            [
                486,
                887
            ],
            [
                486,
                906
            ]
        ]
    },
    {
        "coordinates": [
            [
                376,
                926
            ],
            [
                376,
                904
            ],
            [
                377,
                903
            ],
            [
                377,
                901
            ],
            [
                381,
                901
            ],
            [
                382,
                900
            ],
            [
                382,
                872
            ],
            [
                400,
                872
            ],
            [
                401,
                873
            ],
            [
                410,
                873
            ],
            [
                410,
                885
            ],
            [
                409,
                886
            ],
            [
                409,
                912
            ],
            [
                406,
                912
            ],
            [
                405,
                911
            ],
            [
                400,
                911
            ],
            [
                399,
                912
            ],
            [
                399,
                922
            ],
            [
                398,
                923
            ],
            [
                398,
                926
            ]
        ]
    },
    {
        "coordinates": [
            [
                980,
                936
            ],
            [
                980,
                932
            ],
            [
                979,
                931
            ],
            [
                957,
                931
            ],
            [
                957,
                910
            ],
            [
                956,
                909
            ],
            [
                952,
                909
            ],
            [
                952,
                904
            ],
            [
                951,
                903
            ],
            [
                951,
                873
            ],
            [
                955,
                873
            ],
            [
                957,
                871
            ],
            [
                957,
                866
            ],
            [
                978,
                866
            ],
            [
                979,
                865
            ],
            [
                979,
                860
            ],
            [
                1014,
                860
            ],
            [
                1015,
                859
            ],
            [
                1016,
                859
            ],
            [
                1016,
                866
            ],
            [
                1017,
                867
            ],
            [
                1023,
                867
            ],
            [
                1023,
                906
            ],
            [
                995,
                906
            ],
            [
                994,
                907
            ],
            [
                994,
                936
            ]
        ]
    },
    {
        "coordinates": [
            [
                212,
                957
            ],
            [
                212,
                948
            ],
            [
                211,
                947
            ],
            [
                211,
                908
            ],
            [
                210,
                907
            ],
            [
                210,
                891
            ],
            [
                211,
                890
            ],
            [
                241,
                890
            ],
            [
                241,
                916
            ],
            [
                242,
                917
            ],
            [
                242,
                956
            ],
            [
                243,
                957
            ]
        ]
    },
    {
        "coordinates": [
            [
                426,
                973
            ],
            [
                426,
                950
            ],
            [
                461,
                950
            ],
            [
                461,
                973
            ]
        ]
    },
    {
        "coordinates": [
            [
                216,
                1013
            ],
            [
                216,
                983
            ],
            [
                251,
                983
            ],
            [
                252,
                982
            ],
            [
                252,
                993
            ],
            [
                253,
                994
            ],
            [
                253,
                1013
            ]
        ]
    },
    {
        "coordinates": [
            [
                993,
                1024
            ],
            [
                993,
                1007
            ],
            [
                992,
                1006
            ],
            [
                992,
                974
            ],
            [
                995,
                971
            ],
            [
                995,
                970
            ],
            [
                998,
                967
            ],
            [
                998,
                966
            ],
            [
                1000,
                964
            ],
            [
                1000,
                963
            ],
            [
                1003,
                960
            ],
            [
                1003,
                959
            ],
            [
                1023,
                959
            ],
            [
                1023,
                1024
            ]
        ]
    },
    {
        "coordinates": [
            [
                682,
                1024
            ],
            [
                682,
                1016
            ],
            [
                696,
                1016
            ],
            [
                698,
                1014
            ],
            [
                698,
                1005
            ],
            [
                712,
                1005
            ],
            [
                713,
                1004
            ],
            [
                712,
                1003
            ],
            [
                681,
                1003
            ],
            [
                680,
                1004
            ],
            [
                650,
                1004
            ],
            [
                650,
                967
            ],
            [
                661,
                967
            ],
            [
                662,
                966
            ],
            [
                662,
                944
            ],
            [
                769,
                944
            ],
            [
                770,
                943
            ],
            [
                820,
                943
            ],
            [
                820,
                962
            ],
            [
                821,
                963
            ],
            [
                821,
                1003
            ],
            [
                737,
                1003
            ],
            [
                736,
                1004
            ],
            [
                714,
                1004
            ],
            [
                713,
                1005
            ],
            [
                714,
                1006
            ],
            [
                722,
                1006
            ],
            [
                722,
                1017
            ],
            [
                721,
                1018
            ],
            [
                721,
                1024
            ]
        ]
    },
    {
        "coordinates": [
            [
                577,
                1024
            ],
            [
                577,
                968
            ],
            [
                576,
                967
            ],
            [
                576,
                905
            ],
            [
                575,
                904
            ],
            [
                575,
                863
            ],
            [
                622,
                863
            ],
            [
                622,
                903
            ],
            [
                623,
                904
            ],
            [
                623,
                966
            ],
            [
                624,
                967
            ],
            [
                624,
                1024
            ]
        ]
    },
    {
        "coordinates": [
            [
                107,
                1024
            ],
            [
                107,
                982
            ],
            [
                145,
                982
            ],
            [
                145,
                1024
            ]
        ]
    },
    {
        "coordinates": [
            [
                9,
                1024
            ],
            [
                9,
                960
            ],
            [
                10,
                959
            ],
            [
                10,
                945
            ],
            [
                29,
                945
            ],
            [
                29,
                981
            ],
            [
                28,
                982
            ],
            [
                28,
                1024
            ]
        ]
    }
]